{"aircraft_id": 422, "airlines_name": "AirIndia", "travel": {"destination_city": "Norway", "source_city": "Norway"}, "aircraftEmergency_phone": "(499)526-0123", "time": {"departure_time": "21:50:01", "arrival_time": "13:12:51"}},
{"aircraft_id": 355, "airlines_name": null, "travel": {"destination_city": "Singapore", "source_city": "Singapore"}, "aircraftEmergency_phone": "467-606-1123x7548", "time": {"departure_time": "16:59:00", "arrival_time": "17:19:57"}},
{"aircraft_id": 424, "airlines_name": "AirIndia", "travel": {"destination_city": "Singapore", "source_city": "Amsterdam"}, "aircraftEmergency_phone": "001-907-654-8202", "time": {"departure_time": "17:51:59", "arrival_time": "01:51:53"}},
{"aircraft_id": 701, "airlines_name": null, "travel": {"destination_city": "Amsterdam", "source_city": "Amsterdam"}, "aircraftEmergency_phone": "769-649-7898x6578", "time": {"departure_time": "11:40:47", "arrival_time": "11:00:52"}},
{"aircraft_id": 549, "airlines_name": "AirIndia", "travel": {"destination_city": "Norway", "source_city": "Amsterdam"}, "aircraftEmergency_phone": "+1-652-428-3510x97523", "time": {"departure_time": "02:16:36", "arrival_time": "22:44:29"}},
{"aircraft_id": 358, "airlines_name": null, "travel": {"destination_city": "Singapore", "source_city": "Norway"}, "aircraftEmergency_phone": "(647)402-1880", "time": {"departure_time": "18:22:41", "arrival_time": "17:06:56"}},
{"aircraft_id": 916, "airlines_name": "AirIndia", "travel": {"destination_city": "Norway", "source_city": "Norway"}, "aircraftEmergency_phone": "+1-222-561-9423x65678", "time": {"departure_time": "22:12:47", "arrival_time": "19:37:06"}},
{"aircraft_id": 947, "airlines_name": null, "travel": {"destination_city": "Amsterdam", "source_city": "Singapore"}, "aircraftEmergency_phone": "001-684-632-9725x610", "time": {"departure_time": "17:12:15", "arrival_time": "02:31:15"}},
{"aircraft_id": 669, "airlines_name": "AirIndia", "travel": {"destination_city": "Amsterdam", "source_city": "Amsterdam"}, "aircraftEmergency_phone": "675.315.3544", "time": {"departure_time": "18:26:36", "arrival_time": "12:48:56"}},
{"aircraft_id": 702, "airlines_name": "Indigo", "travel": {"destination_city": "India", "source_city": "Norway"}, "aircraftEmergency_phone": "891.432.3508x38068", "time": {"departure_time": "17:47:46", "arrival_time": "08:45:47"}},
{"aircraft_id": 348, "airlines_name": "AirIndia", "travel": {"destination_city": "Singapore", "source_city": "Amsterdam"}, "aircraftEmergency_phone": "001-475-240-3564x339", "time": {"departure_time": "10:44:57", "arrival_time": "09:55:56"}},
{"aircraft_id": 659, "airlines_name": null, "travel": {"destination_city": "Singapore", "source_city": "Singapore"}, "aircraftEmergency_phone": "462.806.8722x653", "time": {"departure_time": "03:41:56", "arrival_time": "00:00:11"}},
{"aircraft_id": 290, "airlines_name": "AirIndia", "travel": {"destination_city": "Norway", "source_city": "Singapore"}, "aircraftEmergency_phone": "+1-628-568-6459x76590", "time": {"departure_time": "11:43:26", "arrival_time": "01:38:44"}},
{"aircraft_id": 258, "airlines_name": "Quatar", "travel": {"destination_city": "Norway", "source_city": "Norway"}, "aircraftEmergency_phone": "001-506-413-1772x062", "time": {"departure_time": "07:15:27", "arrival_time": "12:56:37"}},
{"aircraft_id": 438, "airlines_name": "Quatar", "travel": {"destination_city": "Norway", "source_city": "Amsterdam"}, "aircraftEmergency_phone": "+1-239-890-8425x9943", "time": {"departure_time": "16:56:32", "arrival_time": "04:40:13"}},
{"aircraft_id": 472, "airlines_name": null, "travel": {"destination_city": "Amsterdam", "source_city": "Singapore"}, "aircraftEmergency_phone": "708.935.5047", "time": {"departure_time": "06:12:42", "arrival_time": "12:24:13"}},
{"aircraft_id": 993, "airlines_name": "AirIndia", "travel": {"destination_city": "Amsterdam", "source_city": "India"}, "aircraftEmergency_phone": "001-360-495-9442x8386", "time": {"departure_time": "21:18:38", "arrival_time": "19:47:23"}},
{"aircraft_id": 688, "airlines_name": "Indigo", "travel": {"destination_city": "India", "source_city": "Singapore"}, "aircraftEmergency_phone": "602-572-3029", "time": {"departure_time": "19:15:14", "arrival_time": "12:09:48"}},
{"aircraft_id": 381, "airlines_name": null, "travel": {"destination_city": "Norway", "source_city": "India"}, "aircraftEmergency_phone": "001-569-367-0632x39181", "time": {"departure_time": "01:26:37", "arrival_time": "02:31:32"}},
{"aircraft_id": 618, "airlines_name": "Indigo", "travel": {"destination_city": "India", "source_city": "Amsterdam"}, "aircraftEmergency_phone": "866.948.8483", "time": {"departure_time": "10:18:37", "arrival_time": "07:09:54"}},
{"aircraft_id": 140, "airlines_name": "Indigo", "travel": {"destination_city": "India", "source_city": "Amsterdam"}, "aircraftEmergency_phone": "+1-204-712-6545x44630", "time": {"departure_time": "10:13:15", "arrival_time": "23:26:47"}},
{"aircraft_id": 680, "airlines_name": null, "travel": {"destination_city": "Singapore", "source_city": "Norway"}, "aircraftEmergency_phone": "001-620-259-7892x923", "time": {"departure_time": "02:11:42", "arrival_time": "02:56:26"}},
{"aircraft_id": 796, "airlines_name": "AirIndia", "travel": {"destination_city": "Singapore", "source_city": "Singapore"}, "aircraftEmergency_phone": "590.528.4261x283", "time": {"departure_time": "11:14:47", "arrival_time": "12:50:44"}},
{"aircraft_id": 556, "airlines_name": null, "travel": {"destination_city": "India", "source_city": "Singapore"}, "aircraftEmergency_phone": "719-655-6811", "time": {"departure_time": "01:45:20", "arrival_time": "03:59:02"}},
{"aircraft_id": 34, "airlines_name": null, "travel": {"destination_city": "Amsterdam", "source_city": "Singapore"}, "aircraftEmergency_phone": "801-768-6498x698", "time": {"departure_time": "22:50:33", "arrival_time": "09:55:17"}},
{"aircraft_id": 204, "airlines_name": "AirIndia", "travel": {"destination_city": "Amsterdam", "source_city": "Norway"}, "aircraftEmergency_phone": "(526)933-3356x95517", "time": {"departure_time": "07:33:15", "arrival_time": "22:02:55"}},
{"aircraft_id": 792, "airlines_name": "Quatar", "travel": {"destination_city": "Singapore", "source_city": "Singapore"}, "aircraftEmergency_phone": "+1-792-630-7392x17801", "time": {"departure_time": "14:48:27", "arrival_time": "21:05:28"}},
{"aircraft_id": 707, "airlines_name": "Quatar", "travel": {"destination_city": "Amsterdam", "source_city": "Singapore"}, "aircraftEmergency_phone": "344-243-7836x3330", "time": {"departure_time": "06:45:07", "arrival_time": "09:56:58"}},
{"aircraft_id": 686, "airlines_name": "SingaporeAirlines", "travel": {"destination_city": "India", "source_city": "Amsterdam"}, "aircraftEmergency_phone": "(340)342-5644x9088", "time": {"departure_time": "23:16:27", "arrival_time": "08:41:19"}},
{"aircraft_id": 496, "airlines_name": "Quatar", "travel": {"destination_city": "Norway", "source_city": "Norway"}, "aircraftEmergency_phone": "(477)752-7384x0966", "time": {"departure_time": "22:04:26", "arrival_time": "18:58:46"}},
